mcp_jenkins/__init__.py
mcp_jenkins/core/__init__.py
mcp_jenkins/core/lifespan.py
mcp_jenkins/core/middleware.py
mcp_jenkins/jenkins/__init__.py
mcp_jenkins/jenkins/rest_client.py
mcp_jenkins/jenkins/rest_endpoint.py
mcp_jenkins/jenkins/model/build.py
mcp_jenkins/jenkins/model/item.py
mcp_jenkins/jenkins/model/node.py
mcp_jenkins/jenkins/model/queue.py
mcp_jenkins/server/__init__.py
mcp_jenkins/server/build.py
mcp_jenkins/server/item.py
mcp_jenkins/server/node.py
mcp_jenkins/server/queue.py
mcp_jenkins-1.0.1.dist-info/licenses/LICENSE
mcp_jenkins-1.0.1.dist-info/METADATA
mcp_jenkins-1.0.1.dist-info/WHEEL
mcp_jenkins-1.0.1.dist-info/entry_points.txt
mcp_jenkins-1.0.1.dist-info/top_level.txt
mcp_jenkins-1.0.1.dist-info/RECORD
