Metadata-Version: 2.4
Name: mcp-jenkins
Version: 1.0.1
Summary: The Model Context Protocol (MCP) is an open-source implementation that bridges Jenkins with AI language models following Anthropic's MCP specification. This project enables secure, contextual AI interactions with Jenkins tools while maintaining data privacy and security.
Author-email: lanbaoshen <lanbaoshen@icloud.com>
Requires-Python: >=3.11
License-File: LICENSE
Requires-Dist: beautifulsoup4>=4.14.3
Requires-Dist: fastmcp>=2.14.2
Requires-Dist: loguru>=0.7.3
Dynamic: license-file
